{


"Patient": [
{"id":"PT-1","ref":[],"code":[],"name":"Joy Keva Toy","gender":"female","birthDate":"2020-12-21","address":"971 Bosco Vale Suite 59, Granby, MA, 01033","maritalStatus":"Never Married","multipleBirthBoolean":false,"communication":"English (United States)","stat":"living"}],

"Encounter": [
{"id":"EN-2","date":"2020-12-21T02:17:05","ref":[],"code":["Well child visit","ambulatory"],"stat":"finished","provider":"performer Dr. Arla Fritsch","facility":"RIVER'S EDGE PRIMARY CARE LLC","endDate":"2020-12-21T02:32:05"},
{"id":"EN-32","date":"2021-01-25T02:17:05","ref":[],"code":["Well child visit","ambulatory"],"stat":"finished","provider":"performer Dr. Arla Fritsch","facility":"RIVER'S EDGE PRIMARY CARE LLC","endDate":"2021-01-25T02:32:05"},
{"id":"EN-49","date":"2021-03-29T03:17:05","ref":[],"code":["Well child visit","ambulatory"],"stat":"finished","provider":"performer Dr. Arla Fritsch","facility":"RIVER'S EDGE PRIMARY CARE LLC","endDate":"2021-03-29T03:32:05"},
{"id":"EN-69","date":"2021-05-31T03:17:05","ref":[],"code":["Well child visit","ambulatory"],"stat":"finished","provider":"performer Dr. Arla Fritsch","facility":"RIVER'S EDGE PRIMARY CARE LLC","endDate":"2021-05-31T03:32:05"},
{"id":"EN-89","date":"2021-08-30T03:17:05","ref":[],"code":["Well child visit","ambulatory"],"stat":"finished","provider":"performer Dr. Arla Fritsch","facility":"RIVER'S EDGE PRIMARY CARE LLC","endDate":"2021-08-30T03:32:05"},
{"id":"EN-109","date":"2021-11-29T02:17:05","ref":[],"code":["Well child visit","ambulatory"],"stat":"finished","provider":"performer Dr. Arla Fritsch","facility":"RIVER'S EDGE PRIMARY CARE LLC","endDate":"2021-11-29T02:32:05"},
{"id":"EN-124","date":"2022-02-28T02:17:05","ref":[],"code":["Well child visit","ambulatory"],"stat":"finished","provider":"performer Dr. Arla Fritsch","facility":"RIVER'S EDGE PRIMARY CARE LLC","endDate":"2022-02-28T02:32:05"},
{"id":"EN-145","date":"2022-05-30T03:17:05","ref":[],"code":["Well child visit","ambulatory"],"stat":"finished","provider":"performer Dr. Arla Fritsch","facility":"RIVER'S EDGE PRIMARY CARE LLC","endDate":"2022-05-30T03:32:05"},
{"id":"EN-162","date":"2022-11-28T02:17:05","ref":[],"code":["Well child visit","ambulatory"],"stat":"finished","provider":"performer Dr. Arla Fritsch","facility":"RIVER'S EDGE PRIMARY CARE LLC","endDate":"2022-11-28T02:32:05"},
{"id":"EN-178","date":"2023-05-29T03:17:05","ref":[],"code":["Well child visit","ambulatory"],"stat":"finished","provider":"performer Dr. Arla Fritsch","facility":"RIVER'S EDGE PRIMARY CARE LLC","endDate":"2023-05-29T03:32:05"},
{"id":"EN-197","date":"2023-11-27T02:17:05","ref":[],"code":["Well child visit","ambulatory"],"stat":"finished","provider":"performer Dr. Arla Fritsch","facility":"RIVER'S EDGE PRIMARY CARE LLC","endDate":"2023-11-27T02:32:05"},
{"id":"EN-216","date":"2024-05-27T03:17:05","ref":[],"code":["Well child visit","ambulatory"],"stat":"finished","provider":"performer Dr. Arla Fritsch","facility":"RIVER'S EDGE PRIMARY CARE LLC","endDate":"2024-05-27T03:32:05"}],

"Condition": [
{"id":"CN-3","date":"2020-12-21T02:17:05","ref":["EN-2"],"code":["Medication review due (situation)"],"onsetDateTime":"2020-12-21T02:17:05","abatementDateTime":"2020-12-21T02:17:05","stat":"confirmed"},
{"id":"CN-33","date":"2021-01-25T02:17:05","ref":["EN-32"],"code":["Medication review due (situation)"],"onsetDateTime":"2021-01-25T02:17:05","abatementDateTime":"2022-02-28T02:17:05","stat":"confirmed"},
{"id":"CN-146","date":"2022-05-30T03:17:05","ref":["EN-145"],"code":["Medication review due (situation)"],"onsetDateTime":"2022-05-30T03:17:05","abatementDateTime":"2023-05-29T03:17:05","stat":"confirmed"},
{"id":"CN-198","date":"2023-11-27T02:17:05","ref":["EN-197"],"code":["Medication review due (situation)"],"onsetDateTime":"2023-11-27T02:17:05","stat":"confirmed"}],

"DiagnosticReport": [
{"id":"DR-27","date":"2020-12-21T02:17:05","ref":["EN-2","OB-13","OB-14","OB-15","OB-16","OB-17","OB-18","OB-19","OB-20","OB-21","OB-22","OB-23"],"code":["CBC panel - Blood by Automated count"],"stat":"final","category":["v2-0074:LABlab"],"provider":"RIVER'S EDGE PRIMARY CARE LLC"},
{"id":"PR-25","date":"2020-12-21T02:17:05","ref":["EN-2"],"code":["Medication reconciliation"],"stat":"completed","endDate":"2020-12-21T02:32:05"},
{"id":"PR-135","date":"2022-02-28T02:17:05","ref":["EN-124"],"code":["Medication reconciliation"],"stat":"completed","endDate":"2022-02-28T02:32:05"},
{"id":"PR-191","date":"2023-05-29T03:17:05","ref":["EN-178"],"code":["Medication reconciliation"],"stat":"completed","endDate":"2023-05-29T03:32:05"}],

"Observation": [
{"id":"OB-4","date":"2020-12-21T02:17:05","ref":["EN-2"],"code":["Body Height is 51 cm"],"stat":"final","category":"Vital"},
{"id":"OB-5","date":"2020-12-21T02:17:05","ref":["EN-2"],"code":["Pain severity - 0-10 verbal numeric rating [Score] - Reported is 0 {score}"],"stat":"final","category":"Vital"},
{"id":"OB-6","date":"2020-12-21T02:17:05","ref":["EN-2"],"code":["Body Weight is 3.5 kg"],"stat":"final","category":"Vital"},
{"id":"OB-7","date":"2020-12-21T02:17:05","ref":["EN-2"],"code":["Weight-for-length Per age and sex is 26.814 %"],"stat":"final","category":"Vital"},
{"id":"OB-8","date":"2020-12-21T02:17:05","ref":["EN-2"],"code":["Head Occipital-frontal circumference Percentile is 41.65 %"],"stat":"final","category":"Vital"},
{"id":"OB-9","date":"2020-12-21T02:17:05","ref":["EN-2"],"code":["Head Occipital-frontal circumference is 34.37 cm"],"stat":"final","category":"Vital"},
{"id":"OB-10","date":"2020-12-21T02:17:05","ref":["EN-2"],"code":["Blood pressure panel with all children optional","Diastolic Blood Pressure 82 mm[Hg]","Systolic Blood Pressure 134 mm[Hg]"],"stat":"final","category":"Vital"},
{"id":"OB-11","date":"2020-12-21T02:17:05","ref":["EN-2"],"code":["Heart rate is 75 /min"],"stat":"final","category":"Vital"},
{"id":"OB-12","date":"2020-12-21T02:17:05","ref":["EN-2"],"code":["Respiratory rate is 13 /min"],"stat":"final","category":"Vital"},
{"id":"OB-13","date":"2020-12-21T02:17:05","ref":["EN-2"],"code":["Leukocytes [#/volume] in Blood by Automated count is 6.8783 10*3/uL"],"stat":"final","category":"Laboratory"},
{"id":"OB-14","date":"2020-12-21T02:17:05","ref":["EN-2"],"code":["Erythrocytes [#/volume] in Blood by Automated count is 4.5089 10*6/uL"],"stat":"final","category":"Laboratory"},
{"id":"OB-15","date":"2020-12-21T02:17:05","ref":["EN-2"],"code":["Hemoglobin [Mass/volume] in Blood is 16.621 g/dL"],"stat":"final","category":"Laboratory"},
{"id":"OB-16","date":"2020-12-21T02:17:05","ref":["EN-2"],"code":["Hematocrit [Volume Fraction] of Blood by Automated count is 36.238 %"],"stat":"final","category":"Laboratory"},
{"id":"OB-17","date":"2020-12-21T02:17:05","ref":["EN-2"],"code":["MCV [Entitic volume] by Automated count is 93.046 fL"],"stat":"final","category":"Laboratory"},
{"id":"OB-18","date":"2020-12-21T02:17:05","ref":["EN-2"],"code":["MCH [Entitic mass] by Automated count is 29.122 pg"],"stat":"final","category":"Laboratory"},
{"id":"OB-19","date":"2020-12-21T02:17:05","ref":["EN-2"],"code":["MCHC [Mass/volume] by Automated count is 34.911 g/dL"],"stat":"final","category":"Laboratory"},
{"id":"OB-20","date":"2020-12-21T02:17:05","ref":["EN-2"],"code":["Erythrocyte distribution width [Entitic volume] by Automated count is 45.535 fL"],"stat":"final","category":"Laboratory"},
{"id":"OB-21","date":"2020-12-21T02:17:05","ref":["EN-2"],"code":["Platelets [#/volume] in Blood by Automated count is 306.86 10*3/uL"],"stat":"final","category":"Laboratory"},
{"id":"OB-22","date":"2020-12-21T02:17:05","ref":["EN-2"],"code":["Platelet distribution width [Entitic volume] in Blood by Automated count is 289.53 fL"],"stat":"final","category":"Laboratory"},
{"id":"OB-23","date":"2020-12-21T02:17:05","ref":["EN-2"],"code":["Platelet mean volume [Entitic volume] in Blood by Automated count is 10.614 fL"],"stat":"final","category":"Laboratory"},
{"id":"OB-24","date":"2020-12-21T02:17:05","ref":["EN-2"],"code":["Tobacco smoking status is Never smoked tobacco (finding)"],"stat":"final","category":"Social"},
{"id":"OB-34","date":"2021-01-25T02:17:05","ref":["EN-32"],"code":["Body Height is 54.6 cm"],"stat":"final","category":"Vital"},
{"id":"OB-35","date":"2021-01-25T02:17:05","ref":["EN-32"],"code":["Pain severity - 0-10 verbal numeric rating [Score] - Reported is 4 {score}"],"stat":"final","category":"Vital"},
{"id":"OB-36","date":"2021-01-25T02:17:05","ref":["EN-32"],"code":["Body Weight is 4.2 kg"],"stat":"final","category":"Vital"},
{"id":"OB-37","date":"2021-01-25T02:17:05","ref":["EN-32"],"code":["Weight-for-length Per age and sex is 10.291 %"],"stat":"final","category":"Vital"},
{"id":"OB-38","date":"2021-01-25T02:17:05","ref":["EN-32"],"code":["Head Occipital-frontal circumference Percentile is 41.65 %"],"stat":"final","category":"Vital"},
{"id":"OB-39","date":"2021-01-25T02:17:05","ref":["EN-32"],"code":["Head Occipital-frontal circumference is 37.68 cm"],"stat":"final","category":"Vital"},
{"id":"OB-40","date":"2021-01-25T02:17:05","ref":["EN-32"],"code":["Blood pressure panel with all children optional","Diastolic Blood Pressure 83 mm[Hg]","Systolic Blood Pressure 138 mm[Hg]"],"stat":"final","category":"Vital"},
{"id":"OB-41","date":"2021-01-25T02:17:05","ref":["EN-32"],"code":["Heart rate is 82 /min"],"stat":"final","category":"Vital"},
{"id":"OB-42","date":"2021-01-25T02:17:05","ref":["EN-32"],"code":["Respiratory rate is 16 /min"],"stat":"final","category":"Vital"},
{"id":"OB-43","date":"2021-01-25T02:17:05","ref":["EN-32"],"code":["Tobacco smoking status is Never smoked tobacco (finding)"],"stat":"final","category":"Social"},
{"id":"OB-50","date":"2021-03-29T03:17:05","ref":["EN-49"],"code":["Body Height is 59.8 cm"],"stat":"final","category":"Vital"},
{"id":"OB-51","date":"2021-03-29T03:17:05","ref":["EN-49"],"code":["Pain severity - 0-10 verbal numeric rating [Score] - Reported is 0 {score}"],"stat":"final","category":"Vital"},
{"id":"OB-52","date":"2021-03-29T03:17:05","ref":["EN-49"],"code":["Body Weight is 5.5 kg"],"stat":"final","category":"Vital"},
{"id":"OB-53","date":"2021-03-29T03:17:05","ref":["EN-49"],"code":["Weight-for-length Per age and sex is 17.84 %"],"stat":"final","category":"Vital"},
{"id":"OB-54","date":"2021-03-29T03:17:05","ref":["EN-49"],"code":["Head Occipital-frontal circumference Percentile is 41.65 %"],"stat":"final","category":"Vital"},
{"id":"OB-55","date":"2021-03-29T03:17:05","ref":["EN-49"],"code":["Head Occipital-frontal circumference is 40.19 cm"],"stat":"final","category":"Vital"},
{"id":"OB-56","date":"2021-03-29T03:17:05","ref":["EN-49"],"code":["Blood pressure panel with all children optional","Diastolic Blood Pressure 86 mm[Hg]","Systolic Blood Pressure 132 mm[Hg]"],"stat":"final","category":"Vital"},
{"id":"OB-57","date":"2021-03-29T03:17:05","ref":["EN-49"],"code":["Heart rate is 85 /min"],"stat":"final","category":"Vital"},
{"id":"OB-58","date":"2021-03-29T03:17:05","ref":["EN-49"],"code":["Respiratory rate is 13 /min"],"stat":"final","category":"Vital"},
{"id":"OB-59","date":"2021-03-29T03:17:05","ref":["EN-49"],"code":["Tobacco smoking status is Never smoked tobacco (finding)"],"stat":"final","category":"Social"},
{"id":"OB-70","date":"2021-05-31T03:17:05","ref":["EN-69"],"code":["Body Height is 63.7 cm"],"stat":"final","category":"Vital"},
{"id":"OB-71","date":"2021-05-31T03:17:05","ref":["EN-69"],"code":["Pain severity - 0-10 verbal numeric rating [Score] - Reported is 3 {score}"],"stat":"final","category":"Vital"},
{"id":"OB-72","date":"2021-05-31T03:17:05","ref":["EN-69"],"code":["Body Weight is 6.5 kg"],"stat":"final","category":"Vital"},
{"id":"OB-73","date":"2021-05-31T03:17:05","ref":["EN-69"],"code":["Weight-for-length Per age and sex is 21.491 %"],"stat":"final","category":"Vital"},
{"id":"OB-74","date":"2021-05-31T03:17:05","ref":["EN-69"],"code":["Head Occipital-frontal circumference Percentile is 41.65 %"],"stat":"final","category":"Vital"},
{"id":"OB-75","date":"2021-05-31T03:17:05","ref":["EN-69"],"code":["Head Occipital-frontal circumference is 41.81 cm"],"stat":"final","category":"Vital"},
{"id":"OB-76","date":"2021-05-31T03:17:05","ref":["EN-69"],"code":["Blood pressure panel with all children optional","Diastolic Blood Pressure 86 mm[Hg]","Systolic Blood Pressure 129 mm[Hg]"],"stat":"final","category":"Vital"},
{"id":"OB-77","date":"2021-05-31T03:17:05","ref":["EN-69"],"code":["Heart rate is 62 /min"],"stat":"final","category":"Vital"},
{"id":"OB-78","date":"2021-05-31T03:17:05","ref":["EN-69"],"code":["Respiratory rate is 14 /min"],"stat":"final","category":"Vital"},
{"id":"OB-79","date":"2021-05-31T03:17:05","ref":["EN-69"],"code":["Tobacco smoking status is Never smoked tobacco (finding)"],"stat":"final","category":"Social"},
{"id":"OB-90","date":"2021-08-30T03:17:05","ref":["EN-89"],"code":["Body Height is 68.4 cm"],"stat":"final","category":"Vital"},
{"id":"OB-91","date":"2021-08-30T03:17:05","ref":["EN-89"],"code":["Pain severity - 0-10 verbal numeric rating [Score] - Reported is 2 {score}"],"stat":"final","category":"Vital"},
{"id":"OB-92","date":"2021-08-30T03:17:05","ref":["EN-89"],"code":["Body Weight is 7.8 kg"],"stat":"final","category":"Vital"},
{"id":"OB-93","date":"2021-08-30T03:17:05","ref":["EN-89"],"code":["Weight-for-length Per age and sex is 42.549 %"],"stat":"final","category":"Vital"},
{"id":"OB-94","date":"2021-08-30T03:17:05","ref":["EN-89"],"code":["Head Occipital-frontal circumference Percentile is 41.65 %"],"stat":"final","category":"Vital"},
{"id":"OB-95","date":"2021-08-30T03:17:05","ref":["EN-89"],"code":["Head Occipital-frontal circumference is 43.47 cm"],"stat":"final","category":"Vital"},
{"id":"OB-96","date":"2021-08-30T03:17:05","ref":["EN-89"],"code":["Blood pressure panel with all children optional","Diastolic Blood Pressure 84 mm[Hg]","Systolic Blood Pressure 126 mm[Hg]"],"stat":"final","category":"Vital"},
{"id":"OB-97","date":"2021-08-30T03:17:05","ref":["EN-89"],"code":["Heart rate is 79 /min"],"stat":"final","category":"Vital"},
{"id":"OB-98","date":"2021-08-30T03:17:05","ref":["EN-89"],"code":["Respiratory rate is 15 /min"],"stat":"final","category":"Vital"},
{"id":"OB-99","date":"2021-08-30T03:17:05","ref":["EN-89"],"code":["Tobacco smoking status is Never smoked tobacco (finding)"],"stat":"final","category":"Social"},
{"id":"OB-110","date":"2021-11-29T02:17:05","ref":["EN-109"],"code":["Body Height is 72.4 cm"],"stat":"final","category":"Vital"},
{"id":"OB-111","date":"2021-11-29T02:17:05","ref":["EN-109"],"code":["Pain severity - 0-10 verbal numeric rating [Score] - Reported is 2 {score}"],"stat":"final","category":"Vital"},
{"id":"OB-112","date":"2021-11-29T02:17:05","ref":["EN-109"],"code":["Body Weight is 8.9 kg"],"stat":"final","category":"Vital"},
{"id":"OB-113","date":"2021-11-29T02:17:05","ref":["EN-109"],"code":["Weight-for-length Per age and sex is 51.286 %"],"stat":"final","category":"Vital"},
{"id":"OB-114","date":"2021-11-29T02:17:05","ref":["EN-109"],"code":["Head Occipital-frontal circumference Percentile is 41.65 %"],"stat":"final","category":"Vital"},
{"id":"OB-115","date":"2021-11-29T02:17:05","ref":["EN-109"],"code":["Head Occipital-frontal circumference is 44.61 cm"],"stat":"final","category":"Vital"},
{"id":"OB-116","date":"2021-11-29T02:17:05","ref":["EN-109"],"code":["Blood pressure panel with all children optional","Diastolic Blood Pressure 83 mm[Hg]","Systolic Blood Pressure 128 mm[Hg]"],"stat":"final","category":"Vital"},
{"id":"OB-117","date":"2021-11-29T02:17:05","ref":["EN-109"],"code":["Heart rate is 69 /min"],"stat":"final","category":"Vital"},
{"id":"OB-118","date":"2021-11-29T02:17:05","ref":["EN-109"],"code":["Respiratory rate is 16 /min"],"stat":"final","category":"Vital"},
{"id":"OB-119","date":"2021-11-29T02:17:05","ref":["EN-109"],"code":["Tobacco smoking status is Never smoked tobacco (finding)"],"stat":"final","category":"Social"},
{"id":"OB-125","date":"2022-02-28T02:17:05","ref":["EN-124"],"code":["Body Height is 75.8 cm"],"stat":"final","category":"Vital"},
{"id":"OB-126","date":"2022-02-28T02:17:05","ref":["EN-124"],"code":["Pain severity - 0-10 verbal numeric rating [Score] - Reported is 1 {score}"],"stat":"final","category":"Vital"},
{"id":"OB-127","date":"2022-02-28T02:17:05","ref":["EN-124"],"code":["Body Weight is 9.7 kg"],"stat":"final","category":"Vital"},
{"id":"OB-128","date":"2022-02-28T02:17:05","ref":["EN-124"],"code":["Weight-for-length Per age and sex is 45.354 %"],"stat":"final","category":"Vital"},
{"id":"OB-129","date":"2022-02-28T02:17:05","ref":["EN-124"],"code":["Head Occipital-frontal circumference Percentile is 41.65 %"],"stat":"final","category":"Vital"},
{"id":"OB-130","date":"2022-02-28T02:17:05","ref":["EN-124"],"code":["Head Occipital-frontal circumference is 45.47 cm"],"stat":"final","category":"Vital"},
{"id":"OB-131","date":"2022-02-28T02:17:05","ref":["EN-124"],"code":["Blood pressure panel with all children optional","Diastolic Blood Pressure 84 mm[Hg]","Systolic Blood Pressure 135 mm[Hg]"],"stat":"final","category":"Vital"},
{"id":"OB-132","date":"2022-02-28T02:17:05","ref":["EN-124"],"code":["Heart rate is 66 /min"],"stat":"final","category":"Vital"},
{"id":"OB-133","date":"2022-02-28T02:17:05","ref":["EN-124"],"code":["Respiratory rate is 13 /min"],"stat":"final","category":"Vital"},
{"id":"OB-134","date":"2022-02-28T02:17:05","ref":["EN-124"],"code":["Tobacco smoking status is Never smoked tobacco (finding)"],"stat":"final","category":"Social"},
{"id":"OB-147","date":"2022-05-30T03:17:05","ref":["EN-145"],"code":["Body Height is 78.9 cm"],"stat":"final","category":"Vital"},
{"id":"OB-148","date":"2022-05-30T03:17:05","ref":["EN-145"],"code":["Pain severity - 0-10 verbal numeric rating [Score] - Reported is 3 {score}"],"stat":"final","category":"Vital"},
{"id":"OB-149","date":"2022-05-30T03:17:05","ref":["EN-145"],"code":["Body Weight is 10.3 kg"],"stat":"final","category":"Vital"},
{"id":"OB-150","date":"2022-05-30T03:17:05","ref":["EN-145"],"code":["Weight-for-length Per age and sex is 42.053 %"],"stat":"final","category":"Vital"},
{"id":"OB-151","date":"2022-05-30T03:17:05","ref":["EN-145"],"code":["Head Occipital-frontal circumference Percentile is 41.65 %"],"stat":"final","category":"Vital"},
{"id":"OB-152","date":"2022-05-30T03:17:05","ref":["EN-145"],"code":["Head Occipital-frontal circumference is 46.14 cm"],"stat":"final","category":"Vital"},
{"id":"OB-153","date":"2022-05-30T03:17:05","ref":["EN-145"],"code":["Blood pressure panel with all children optional","Diastolic Blood Pressure 88 mm[Hg]","Systolic Blood Pressure 125 mm[Hg]"],"stat":"final","category":"Vital"},
{"id":"OB-154","date":"2022-05-30T03:17:05","ref":["EN-145"],"code":["Heart rate is 72 /min"],"stat":"final","category":"Vital"},
{"id":"OB-155","date":"2022-05-30T03:17:05","ref":["EN-145"],"code":["Respiratory rate is 12 /min"],"stat":"final","category":"Vital"},
{"id":"OB-156","date":"2022-05-30T03:17:05","ref":["EN-145"],"code":["Tobacco smoking status is Never smoked tobacco (finding)"],"stat":"final","category":"Social"},
{"id":"OB-163","date":"2022-11-28T02:17:05","ref":["EN-162"],"code":["Body Height is 84.4 cm"],"stat":"final","category":"Vital"},
{"id":"OB-164","date":"2022-11-28T02:17:05","ref":["EN-162"],"code":["Pain severity - 0-10 verbal numeric rating [Score] - Reported is 2 {score}"],"stat":"final","category":"Vital"},
{"id":"OB-165","date":"2022-11-28T02:17:05","ref":["EN-162"],"code":["Body Weight is 11.3 kg"],"stat":"final","category":"Vital"},
{"id":"OB-166","date":"2022-11-28T02:17:05","ref":["EN-162"],"code":["Weight-for-length Per age and sex is 37.885 %"],"stat":"final","category":"Vital"},
{"id":"OB-167","date":"2022-11-28T02:17:05","ref":["EN-162"],"code":["Head Occipital-frontal circumference Percentile is 41.65 %"],"stat":"final","category":"Vital"},
{"id":"OB-168","date":"2022-11-28T02:17:05","ref":["EN-162"],"code":["Head Occipital-frontal circumference is 47.11 cm"],"stat":"final","category":"Vital"},
{"id":"OB-169","date":"2022-11-28T02:17:05","ref":["EN-162"],"code":["Blood pressure panel with all children optional","Diastolic Blood Pressure 87 mm[Hg]","Systolic Blood Pressure 126 mm[Hg]"],"stat":"final","category":"Vital"},
{"id":"OB-170","date":"2022-11-28T02:17:05","ref":["EN-162"],"code":["Heart rate is 88 /min"],"stat":"final","category":"Vital"},
{"id":"OB-171","date":"2022-11-28T02:17:05","ref":["EN-162"],"code":["Respiratory rate is 16 /min"],"stat":"final","category":"Vital"},
{"id":"OB-172","date":"2022-11-28T02:17:05","ref":["EN-162"],"code":["Tobacco smoking status is Never smoked tobacco (finding)"],"stat":"final","category":"Social"},
{"id":"OB-179","date":"2023-05-29T03:17:05","ref":["EN-178"],"code":["Body Height is 88.5 cm"],"stat":"final","category":"Vital"},
{"id":"OB-180","date":"2023-05-29T03:17:05","ref":["EN-178"],"code":["Pain severity - 0-10 verbal numeric rating [Score] - Reported is 1 {score}"],"stat":"final","category":"Vital"},
{"id":"OB-181","date":"2023-05-29T03:17:05","ref":["EN-178"],"code":["Body Weight is 12.4 kg"],"stat":"final","category":"Vital"},
{"id":"OB-182","date":"2023-05-29T03:17:05","ref":["EN-178"],"code":["Weight-for-length Per age and sex is 38.324 %"],"stat":"final","category":"Vital"},
{"id":"OB-183","date":"2023-05-29T03:17:05","ref":["EN-178"],"code":["Head Occipital-frontal circumference Percentile is 41.65 %"],"stat":"final","category":"Vital"},
{"id":"OB-184","date":"2023-05-29T03:17:05","ref":["EN-178"],"code":["Head Occipital-frontal circumference is 47.78 cm"],"stat":"final","category":"Vital"},
{"id":"OB-185","date":"2023-05-29T03:17:05","ref":["EN-178"],"code":["Body mass index (BMI) [Ratio] is 15.86 kg/m2"],"stat":"final","category":"Vital"},
{"id":"OB-186","date":"2023-05-29T03:17:05","ref":["EN-178"],"code":["Body mass index (BMI) [Percentile] Per age and sex is 43.712 %"],"stat":"final","category":"Vital"},
{"id":"OB-187","date":"2023-05-29T03:17:05","ref":["EN-178"],"code":["Blood pressure panel with all children optional","Diastolic Blood Pressure 83 mm[Hg]","Systolic Blood Pressure 125 mm[Hg]"],"stat":"final","category":"Vital"},
{"id":"OB-188","date":"2023-05-29T03:17:05","ref":["EN-178"],"code":["Heart rate is 70 /min"],"stat":"final","category":"Vital"},
{"id":"OB-189","date":"2023-05-29T03:17:05","ref":["EN-178"],"code":["Respiratory rate is 13 /min"],"stat":"final","category":"Vital"},
{"id":"OB-190","date":"2023-05-29T03:17:05","ref":["EN-178"],"code":["Tobacco smoking status is Never smoked tobacco (finding)"],"stat":"final","category":"Social"},
{"id":"OB-199","date":"2023-11-27T02:17:05","ref":["EN-197"],"code":["Body Height is 92.5 cm"],"stat":"final","category":"Vital"},
{"id":"OB-200","date":"2023-11-27T02:17:05","ref":["EN-197"],"code":["Pain severity - 0-10 verbal numeric rating [Score] - Reported is 4 {score}"],"stat":"final","category":"Vital"},
{"id":"OB-201","date":"2023-11-27T02:17:05","ref":["EN-197"],"code":["Body Weight is 14.5 kg"],"stat":"final","category":"Vital"},
{"id":"OB-202","date":"2023-11-27T02:17:05","ref":["EN-197"],"code":["Weight-for-length Per age and sex is 77.595 %"],"stat":"final","category":"Vital"},
{"id":"OB-203","date":"2023-11-27T02:17:05","ref":["EN-197"],"code":["Head Occipital-frontal circumference Percentile is 41.65 %"],"stat":"final","category":"Vital"},
{"id":"OB-204","date":"2023-11-27T02:17:05","ref":["EN-197"],"code":["Head Occipital-frontal circumference is 48.27 cm"],"stat":"final","category":"Vital"},
{"id":"OB-205","date":"2023-11-27T02:17:05","ref":["EN-197"],"code":["Body mass index (BMI) [Ratio] is 16.91 kg/m2"],"stat":"final","category":"Vital"},
{"id":"OB-206","date":"2023-11-27T02:17:05","ref":["EN-197"],"code":["Body mass index (BMI) [Percentile] Per age and sex is 80.064 %"],"stat":"final","category":"Vital"},
{"id":"OB-207","date":"2023-11-27T02:17:05","ref":["EN-197"],"code":["Blood pressure panel with all children optional","Diastolic Blood Pressure 83 mm[Hg]","Systolic Blood Pressure 123 mm[Hg]"],"stat":"final","category":"Vital"},
{"id":"OB-208","date":"2023-11-27T02:17:05","ref":["EN-197"],"code":["Heart rate is 78 /min"],"stat":"final","category":"Vital"},
{"id":"OB-209","date":"2023-11-27T02:17:05","ref":["EN-197"],"code":["Respiratory rate is 13 /min"],"stat":"final","category":"Vital"},
{"id":"OB-210","date":"2023-11-27T02:17:05","ref":["EN-197"],"code":["Tobacco smoking status is Never smoked tobacco (finding)"],"stat":"final","category":"Social"},
{"id":"OB-217","date":"2024-05-27T03:17:05","ref":["EN-216"],"code":["Body Height is 95.9 cm"],"stat":"final","category":"Vital"},
{"id":"OB-218","date":"2024-05-27T03:17:05","ref":["EN-216"],"code":["Pain severity - 0-10 verbal numeric rating [Score] - Reported is 2 {score}"],"stat":"final","category":"Vital"},
{"id":"OB-219","date":"2024-05-27T03:17:05","ref":["EN-216"],"code":["Body Weight is 16.2 kg"],"stat":"final","category":"Vital"},
{"id":"OB-220","date":"2024-05-27T03:17:05","ref":["EN-216"],"code":["Weight-for-length Per age and sex is 83.814 %"],"stat":"final","category":"Vital"},
{"id":"OB-221","date":"2024-05-27T03:17:05","ref":["EN-216"],"code":["Head Occipital-frontal circumference Percentile is 41.65 %"],"stat":"final","category":"Vital"},
{"id":"OB-222","date":"2024-05-27T03:17:05","ref":["EN-216"],"code":["Head Occipital-frontal circumference is 48.3 cm"],"stat":"final","category":"Vital"},
{"id":"OB-223","date":"2024-05-27T03:17:05","ref":["EN-216"],"code":["Body mass index (BMI) [Ratio] is 17.61 kg/m2"],"stat":"final","category":"Vital"},
{"id":"OB-224","date":"2024-05-27T03:17:05","ref":["EN-216"],"code":["Body mass index (BMI) [Percentile] Per age and sex is 91.905 %"],"stat":"final","category":"Vital"},
{"id":"OB-225","date":"2024-05-27T03:17:05","ref":["EN-216"],"code":["Blood pressure panel with all children optional","Diastolic Blood Pressure 82 mm[Hg]","Systolic Blood Pressure 128 mm[Hg]"],"stat":"final","category":"Vital"},
{"id":"OB-226","date":"2024-05-27T03:17:05","ref":["EN-216"],"code":["Heart rate is 71 /min"],"stat":"final","category":"Vital"},
{"id":"OB-227","date":"2024-05-27T03:17:05","ref":["EN-216"],"code":["Respiratory rate is 15 /min"],"stat":"final","category":"Vital"},
{"id":"OB-228","date":"2024-05-27T03:17:05","ref":["EN-216"],"code":["Tobacco smoking status is Never smoked tobacco (finding)"],"stat":"final","category":"Social"}],

"Immunization": [
{"id":"IM-26","date":"2020-12-21T02:17:05","ref":["EN-2"],"code":["Hep B, adolescent or pediatric"],"stat":"completed","primarySource":true},
{"id":"IM-44","date":"2021-01-25T02:17:05","ref":["EN-32"],"code":["Hep B, adolescent or pediatric"],"stat":"completed","primarySource":true},
{"id":"IM-60","date":"2021-03-29T03:17:05","ref":["EN-49"],"code":["Hib (PRP-OMP)"],"stat":"completed","primarySource":true},
{"id":"IM-61","date":"2021-03-29T03:17:05","ref":["EN-49"],"code":["rotavirus, monovalent"],"stat":"completed","primarySource":true},
{"id":"IM-62","date":"2021-03-29T03:17:05","ref":["EN-49"],"code":["IPV"],"stat":"completed","primarySource":true},
{"id":"IM-63","date":"2021-03-29T03:17:05","ref":["EN-49"],"code":["DTaP"],"stat":"completed","primarySource":true},
{"id":"IM-64","date":"2021-03-29T03:17:05","ref":["EN-49"],"code":["Pneumococcal conjugate PCV 13"],"stat":"completed","primarySource":true},
{"id":"IM-80","date":"2021-05-31T03:17:05","ref":["EN-69"],"code":["Hib (PRP-OMP)"],"stat":"completed","primarySource":true},
{"id":"IM-81","date":"2021-05-31T03:17:05","ref":["EN-69"],"code":["rotavirus, monovalent"],"stat":"completed","primarySource":true},
{"id":"IM-82","date":"2021-05-31T03:17:05","ref":["EN-69"],"code":["IPV"],"stat":"completed","primarySource":true},
{"id":"IM-83","date":"2021-05-31T03:17:05","ref":["EN-69"],"code":["DTaP"],"stat":"completed","primarySource":true},
{"id":"IM-84","date":"2021-05-31T03:17:05","ref":["EN-69"],"code":["Pneumococcal conjugate PCV 13"],"stat":"completed","primarySource":true},
{"id":"IM-100","date":"2021-08-30T03:17:05","ref":["EN-89"],"code":["IPV"],"stat":"completed","primarySource":true},
{"id":"IM-101","date":"2021-08-30T03:17:05","ref":["EN-89"],"code":["Influenza, seasonal, injectable, preservative free"],"stat":"completed","primarySource":true},
{"id":"IM-102","date":"2021-08-30T03:17:05","ref":["EN-89"],"code":["DTaP"],"stat":"completed","primarySource":true},
{"id":"IM-103","date":"2021-08-30T03:17:05","ref":["EN-89"],"code":["Pneumococcal conjugate PCV 13"],"stat":"completed","primarySource":true},
{"id":"IM-104","date":"2021-08-30T03:17:05","ref":["EN-89"],"code":["Hep B, adolescent or pediatric"],"stat":"completed","primarySource":true},
{"id":"IM-136","date":"2022-02-28T02:17:05","ref":["EN-124"],"code":["Hib (PRP-OMP)"],"stat":"completed","primarySource":true},
{"id":"IM-137","date":"2022-02-28T02:17:05","ref":["EN-124"],"code":["varicella"],"stat":"completed","primarySource":true},
{"id":"IM-138","date":"2022-02-28T02:17:05","ref":["EN-124"],"code":["MMR"],"stat":"completed","primarySource":true},
{"id":"IM-139","date":"2022-02-28T02:17:05","ref":["EN-124"],"code":["Pneumococcal conjugate PCV 13"],"stat":"completed","primarySource":true},
{"id":"IM-140","date":"2022-02-28T02:17:05","ref":["EN-124"],"code":["Hep A, ped/adol, 2 dose"],"stat":"completed","primarySource":true},
{"id":"IM-157","date":"2022-05-30T03:17:05","ref":["EN-145"],"code":["DTaP"],"stat":"completed","primarySource":true},
{"id":"IM-173","date":"2022-11-28T02:17:05","ref":["EN-162"],"code":["Influenza, seasonal, injectable, preservative free"],"stat":"completed","primarySource":true},
{"id":"IM-192","date":"2023-05-29T03:17:05","ref":["EN-178"],"code":["Hep A, ped/adol, 2 dose"],"stat":"completed","primarySource":true},
{"id":"IM-211","date":"2023-11-27T02:17:05","ref":["EN-197"],"code":["Influenza, seasonal, injectable, preservative free"],"stat":"completed","primarySource":true}],

"Medication": [],

"MedicationAdministration": [],

"AllergyIntolerance": []}