{


"Patient": [
{"id":"PT-1","ref":[],"code":[],"name":"Tequila Milagros Ryan","gender":"female","birthDate":"2010-01-20","address":"186 Torphy Lock, Attleboro, MA, 02861","maritalStatus":"Never Married","multipleBirthBoolean":false,"communication":"English (United States)","stat":"living"}],

"Encounter": [
{"id":"EN-2","date":"2013-06-26T16:00:34","ref":[],"code":["Well child visit","ambulatory"],"stat":"finished","provider":"performer Dr. Morgan Marvin","facility":"FAMILY MEDICINE ASSOCIATES OF SOUTH ATTLEBORO, P.C.","endDate":"2013-06-26T16:18:20"},
{"id":"EN-8","date":"2014-12-31T15:00:34","ref":[],"code":["Well child visit","ambulatory"],"stat":"finished","provider":"performer Dr. Morgan Marvin","facility":"FAMILY MEDICINE ASSOCIATES OF SOUTH ATTLEBORO, P.C.","endDate":"2014-12-31T15:15:34"},
{"id":"EN-28","date":"2015-07-01T16:00:34","ref":[],"code":["Encounter for check up","ambulatory"],"stat":"finished","provider":"performer Dr. Adrienne Schiller","facility":"ARBOUR-FULLER HOSPITAL","endDate":"2015-07-01T16:15:34"},
{"id":"EN-56","date":"2015-07-08T16:00:34","ref":[],"code":["Encounter for symptom","Acute bronchitis (disorder)","ambulatory"],"stat":"finished","provider":"performer Dr. Adrienne Schiller","facility":"ARBOUR-FULLER HOSPITAL","endDate":"2015-07-08T16:15:34"},
{"id":"EN-68","date":"2015-09-24T18:00:34","ref":[],"code":["Encounter for symptom","Acute viral pharyngitis (disorder)","ambulatory"],"stat":"finished","provider":"performer Dr. Adrienne Schiller","facility":"ARBOUR-FULLER HOSPITAL","endDate":"2015-09-24T18:15:34"},
{"id":"EN-76","date":"2016-01-06T15:00:34","ref":[],"code":["Well child visit","ambulatory"],"stat":"finished","provider":"performer Dr. Morgan Marvin","facility":"FAMILY MEDICINE ASSOCIATES OF SOUTH ATTLEBORO, P.C.","endDate":"2016-01-06T15:15:34"},
{"id":"EN-93","date":"2017-01-11T15:00:34","ref":[],"code":["Well child visit","ambulatory"],"stat":"finished","provider":"performer Dr. Morgan Marvin","facility":"FAMILY MEDICINE ASSOCIATES OF SOUTH ATTLEBORO, P.C.","endDate":"2017-01-11T15:15:34"},
{"id":"EN-110","date":"2018-01-17T15:00:34","ref":[],"code":["Well child visit","ambulatory"],"stat":"finished","provider":"performer Dr. Morgan Marvin","facility":"FAMILY MEDICINE ASSOCIATES OF SOUTH ATTLEBORO, P.C.","endDate":"2018-01-17T15:15:34"},
{"id":"EN-126","date":"2019-01-23T15:00:34","ref":[],"code":["Well child visit","ambulatory"],"stat":"finished","provider":"performer Dr. Morgan Marvin","facility":"FAMILY MEDICINE ASSOCIATES OF SOUTH ATTLEBORO, P.C.","endDate":"2019-01-23T15:15:34"},
{"id":"EN-142","date":"2020-01-29T15:00:34","ref":[],"code":["Well child visit","ambulatory"],"stat":"finished","provider":"performer Dr. Morgan Marvin","facility":"FAMILY MEDICINE ASSOCIATES OF SOUTH ATTLEBORO, P.C.","endDate":"2020-01-29T15:15:34"},
{"id":"EN-159","date":"2020-02-05T15:00:34","ref":[],"code":["Encounter for check up","Patient referral for dental care","ambulatory"],"stat":"finished","provider":"performer Dr. Adrienne Schiller","facility":"ARBOUR-FULLER HOSPITAL","endDate":"2020-02-05T17:34:50"},
{"id":"EN-176","date":"2021-02-03T15:00:34","ref":[],"code":["Well child visit","ambulatory"],"stat":"finished","provider":"performer Dr. Morgan Marvin","facility":"FAMILY MEDICINE ASSOCIATES OF SOUTH ATTLEBORO, P.C.","endDate":"2021-02-03T15:15:34"},
{"id":"EN-207","date":"2022-01-12T15:00:34","ref":[],"code":["Urgent care clinic (environment)","ambulatory"],"stat":"finished","provider":"performer Dr. Tabitha Kling","facility":"WOONSOCKET URGENT CARE PC","endDate":"2022-01-12T15:15:34"},
{"id":"EN-225","date":"2022-01-19T15:00:34","ref":[],"code":["Encounter for symptom","Acute bronchitis (disorder)","ambulatory"],"stat":"finished","provider":"performer Dr. Adrienne Schiller","facility":"ARBOUR-FULLER HOSPITAL","endDate":"2022-01-19T15:15:34"},
{"id":"EN-236","date":"2022-01-19T15:00:34","ref":[],"code":["Encounter for check up","Patient referral for dental care","ambulatory"],"stat":"finished","provider":"performer Dr. Adrienne Schiller","facility":"ARBOUR-FULLER HOSPITAL","endDate":"2022-01-19T21:34:48"},
{"id":"EN-262","date":"2022-02-02T15:00:34","ref":[],"code":["Administration of vaccine to produce active immunity","ambulatory"],"stat":"finished","provider":"performer Dr. Adrienne Schiller","facility":"ARBOUR-FULLER HOSPITAL","endDate":"2022-02-02T15:15:34"},
{"id":"EN-268","date":"2022-02-09T15:00:34","ref":[],"code":["Well child visit","ambulatory"],"stat":"finished","provider":"performer Dr. Morgan Marvin","facility":"FAMILY MEDICINE ASSOCIATES OF SOUTH ATTLEBORO, P.C.","endDate":"2022-02-09T15:15:34"},
{"id":"EN-291","date":"2022-02-23T15:00:34","ref":[],"code":["Administration of vaccine to produce active immunity","ambulatory"],"stat":"finished","provider":"performer Dr. Adrienne Schiller","facility":"ARBOUR-FULLER HOSPITAL","endDate":"2022-02-23T15:15:34"},
{"id":"EN-297","date":"2023-02-15T15:00:34","ref":[],"code":["Well child visit","ambulatory"],"stat":"finished","provider":"performer Dr. Morgan Marvin","facility":"FAMILY MEDICINE ASSOCIATES OF SOUTH ATTLEBORO, P.C.","endDate":"2023-02-15T15:30:13"},
{"id":"EN-323","date":"2024-02-21T15:00:34","ref":[],"code":["Well child visit","ambulatory"],"stat":"finished","provider":"performer Dr. Morgan Marvin","facility":"FAMILY MEDICINE ASSOCIATES OF SOUTH ATTLEBORO, P.C.","endDate":"2024-02-21T15:21:55"},
{"id":"EN-347","date":"2024-10-08T16:00:34","ref":[],"code":["Encounter for symptom","Viral sinusitis (disorder)","ambulatory"],"stat":"finished","provider":"performer Dr. Adrienne Schiller","facility":"ARBOUR-FULLER HOSPITAL","endDate":"2024-10-08T16:15:34"}],

"Condition": [
{"id":"CN-3","date":"2013-06-26T16:00:34","ref":["EN-2"],"code":["Medication review due (situation)"],"onsetDateTime":"2013-06-26T16:00:34","abatementDateTime":"2014-12-31T15:00:34","stat":"confirmed"},
{"id":"CN-29","date":"2015-07-01T16:00:34","ref":["EN-28"],"code":["Medication review due (situation)"],"onsetDateTime":"2015-07-01T16:00:34","abatementDateTime":"2015-07-01T16:00:34","stat":"confirmed"},
{"id":"CN-57","date":"2015-07-08T16:00:34","ref":["EN-56"],"code":["Acute bronchitis (disorder)"],"onsetDateTime":"2015-07-08T16:00:34","abatementDateTime":"2015-07-18T16:13:05","stat":"confirmed"},
{"id":"CN-69","date":"2015-09-24T18:00:34","ref":["EN-68"],"code":["Acute viral pharyngitis (disorder)"],"onsetDateTime":"2015-09-24T18:00:34","abatementDateTime":"2015-10-04T20:00:34","stat":"confirmed"},
{"id":"CN-77","date":"2016-01-06T15:00:34","ref":["EN-76"],"code":["Medication review due (situation)"],"onsetDateTime":"2016-01-06T15:00:34","abatementDateTime":"2016-01-06T15:00:34","stat":"confirmed"},
{"id":"CN-94","date":"2017-01-11T15:00:34","ref":["EN-93"],"code":["Medication review due (situation)"],"onsetDateTime":"2017-01-11T15:00:34","abatementDateTime":"2017-01-11T15:00:34","stat":"confirmed"},
{"id":"CN-111","date":"2018-01-17T15:00:34","ref":["EN-110"],"code":["Medication review due (situation)"],"onsetDateTime":"2018-01-17T15:00:34","abatementDateTime":"2019-01-23T15:00:34","stat":"confirmed"},
{"id":"CN-143","date":"2020-01-29T15:00:34","ref":["EN-142"],"code":["Medication review due (situation)"],"onsetDateTime":"2020-01-29T15:00:34","abatementDateTime":"2021-02-03T15:00:34","stat":"confirmed"},
{"id":"CN-208","date":"2022-01-12T15:00:34","ref":["EN-207"],"code":["Medication review due (situation)"],"onsetDateTime":"2022-01-12T15:00:34","abatementDateTime":"2023-02-15T15:00:34","stat":"confirmed"},
{"id":"CN-226","date":"2022-01-19T15:00:34","ref":["EN-225"],"code":["Acute bronchitis (disorder)"],"onsetDateTime":"2022-01-19T15:00:34","abatementDateTime":"2022-01-28T15:00:34","stat":"confirmed"},
{"id":"CN-237","date":"2022-01-19T18:30:31","ref":["EN-236"],"code":["Gingival disease (disorder)"],"onsetDateTime":"2022-01-19T18:30:31","abatementDateTime":"2022-01-19T20:08:19","stat":"confirmed"},
{"id":"CN-269","date":"2022-02-09T16:12:15","ref":["EN-268"],"code":["Risk activity involvement (finding)"],"onsetDateTime":"2022-02-09T16:12:15","abatementDateTime":"2023-02-15T16:45:57","stat":"confirmed"},
{"id":"CN-324","date":"2024-02-21T15:00:34","ref":["EN-323"],"code":["Medication review due (situation)"],"onsetDateTime":"2024-02-21T15:00:34","abatementDateTime":"2024-02-21T15:00:34","stat":"confirmed"},
{"id":"CN-348","date":"2024-10-08T16:00:34","ref":["EN-347"],"code":["Viral sinusitis (disorder)"],"onsetDateTime":"2024-10-08T16:00:34","abatementDateTime":"2024-10-22T16:00:34","stat":"confirmed"}],

"DiagnosticReport": [
{"id":"DR-51","date":"2015-07-01T16:00:34","ref":["EN-28","OB-38","OB-39","OB-40","OB-41","OB-42","OB-43","OB-44","OB-45","OB-46","OB-47","OB-48"],"code":["CBC panel - Blood by Automated count"],"stat":"final","category":["v2-0074:LAB Laboratory"],"provider":"ARBOUR-FULLER HOSPITAL"},
{"id":"DR-202","date":"2021-02-03T15:00:34","ref":["EN-176","OB-185","OB-186","OB-187","OB-188","OB-189","OB-190","OB-191","OB-192","OB-193","OB-194","OB-195"],"code":["CBC panel - Blood by Automated count"],"stat":"final","category":["v2-0074:LAB Laboratory"],"provider":"FAMILY MEDICINE ASSOCIATES OF SOUTH ATTLEBORO, P.C."},
{"id":"DR-286","date":"2022-02-09T15:41:13","ref":["EN-268","OB-279"],"code":["Patient Health Questionnaire-9: Modified for Teens [Reported.PHQ.Teen]"],"stat":"final"},
{"id":"DR-317","date":"2023-02-15T15:30:13","ref":["EN-297","OB-307"],"code":["Generalized anxiety disorder 7 item (GAD-7)"],"stat":"final"},
{"id":"DR-318","date":"2023-02-15T16:11:42","ref":["EN-297","OB-308"],"code":["Patient Health Questionnaire-9: Modified for Teens [Reported.PHQ.Teen]"],"stat":"final"},
{"id":"DR-341","date":"2024-02-21T15:21:55","ref":["EN-323","OB-334"],"code":["Generalized anxiety disorder 7 item (GAD-7)"],"stat":"final"},
{"id":"DR-342","date":"2024-02-21T15:57:02","ref":["EN-323","OB-335"],"code":["Patient Health Questionnaire-9: Modified for Teens [Reported.PHQ.Teen]"],"stat":"final"},
{"id":"DV-167","ref":[],"code":["Dental x-ray system (physical object)"],"stat":"active","deviceName":"Dental x-ray system (physical object)"},
{"id":"DV-249","ref":[],"code":["Operating room (environment)"],"stat":"active","deviceName":"Operating room (environment)"}],

"SupplyDelivery": [
{"id":"SD-168","date":"2020-02-05T15:46:19","ref":[],"code":["Dental equipment (physical object)"],"stat":"completed","type":"Device","quantity":[1]},
{"id":"SD-169","date":"2020-02-05T15:46:19","ref":[],"code":["Conventional release periodontal gel (dose form)"],"stat":"completed","type":"Device","quantity":[1]},
{"id":"SD-170","date":"2020-02-05T15:46:19","ref":[],"code":["Dental floss (physical object)"],"stat":"completed","type":"Device","quantity":[1]},
{"id":"SD-250","date":"2022-01-19T16:36:49","ref":[],"code":["Dental equipment (physical object)"],"stat":"completed","type":"Device","quantity":[1]},
{"id":"SD-251","date":"2022-01-19T16:36:49","ref":[],"code":["Conventional release periodontal gel (dose form)"],"stat":"completed","type":"Device","quantity":[1]},
{"id":"SD-252","date":"2022-01-19T16:36:49","ref":[],"code":["Dental floss (physical object)"],"stat":"completed","type":"Device","quantity":[1]}],

"ImagingStudy": [
{"id":"IS-171","date":"2020-02-05T16:55:57","ref":["EN-159"],"code":["Dental plain X-ray bitewing","Digital Radiography","Structure of region of internal part of mouth (body structure)","Digital Intra-Oral X-Ray Image"],"stat":"available"}],

"CarePlan": [
{"id":"CP-63","date":"2015-07-08T16:13:05","ref":["EN-56"],"code":["Recommendation to avoid exercise at ARBOUR-FULLER HOSPITAL","Deep breathing and coughing exercises (regime/therapy) at ARBOUR-FULLER HOSPITAL","careplan-category assess-plan","Respiratory therapy","Recommendation to avoid exercise","Deep breathing and coughing exercises (regime/therapy)"],"text":"Care Plan for Respiratory therapy.Activities: Respiratory therapyRespiratory therapy","stat":"completed","intent":"order","endDate":"2016-01-06T15:00:34"},
{"id":"CP-231","date":"2022-01-19T15:00:34","ref":["EN-225"],"code":["Recommendation to avoid exercise at ARBOUR-FULLER HOSPITAL","Deep breathing and coughing exercises (regime/therapy) at ARBOUR-FULLER HOSPITAL","careplan-category assess-plan","Respiratory therapy","Recommendation to avoid exercise","Deep breathing and coughing exercises (regime/therapy)"],"text":"Care Plan for Respiratory therapy.Activities: Respiratory therapyRespiratory therapy","stat":"completed","intent":"order","endDate":"2022-02-09T15:00:34"}],

"MedicationRequest": [
{"id":"MR-59","date":"2015-07-08T16:13:05","ref":["EN-56","CN-57"],"code":["Acetaminophen 325 MG Oral Tablet"],"stat":"stopped","intent":"order","requester":"Dr. Adrienne Schiller"},
{"id":"MR-227","date":"2022-01-19T15:00:34","ref":["EN-225","CN-57"],"code":["Acetaminophen 325 MG Oral Tablet"],"stat":"stopped","intent":"order","requester":"Dr. Adrienne Schiller"},
{"id":"MR-254","date":"2022-01-19T20:49:55","ref":["EN-236","MD-253"],"stat":"stopped","intent":"order","requester":"Dr. Adrienne Schiller","reasonCode":["Patient referral for dental care"]}],

"Procedure": [
{"id":"PR-18","date":"2014-12-31T15:00:34","ref":["EN-8"],"code":["Medication reconciliation"],"stat":"completed","endDate":"2014-12-31T15:15:34"},
{"id":"PR-50","date":"2015-07-01T16:00:34","ref":["EN-28"],"code":["Medication reconciliation"],"stat":"completed","endDate":"2015-07-01T16:15:34"},
{"id":"PR-58","date":"2015-07-08T16:00:34","ref":["EN-56","CN-57"],"code":["Measurement of respiratory function"],"stat":"completed","endDate":"2015-07-08T16:13:05"},
{"id":"PR-71","date":"2015-09-24T18:00:34","ref":["EN-68","CN-69"],"code":["Throat culture"],"stat":"completed","endDate":"2015-09-24T18:15:34"},
{"id":"PR-87","date":"2016-01-06T15:00:34","ref":["EN-76"],"code":["Medication reconciliation"],"stat":"completed","endDate":"2016-01-06T15:15:34"},
{"id":"PR-104","date":"2017-01-11T15:00:34","ref":["EN-93"],"code":["Medication reconciliation"],"stat":"completed","endDate":"2017-01-11T15:15:34"},
{"id":"PR-136","date":"2019-01-23T15:00:34","ref":["EN-126"],"code":["Medication reconciliation"],"stat":"completed","endDate":"2019-01-23T15:15:34"},
{"id":"PR-153","date":"2020-01-29T15:00:34","ref":["EN-142"],"code":["Patient referral for dental care"],"stat":"completed","endDate":"2020-01-29T15:13:00"},
{"id":"PR-160","date":"2020-02-05T15:00:34","ref":["EN-159"],"code":["Dental consultation and report"],"stat":"completed","reasonCode":["Patient referral for dental care"],"endDate":"2020-02-05T15:16:33"},
{"id":"PR-161","date":"2020-02-05T15:16:33","ref":["EN-159"],"code":["Dental care (regime/therapy)"],"stat":"completed","reasonCode":["Patient referral for dental care"],"endDate":"2020-02-05T15:46:19"},
{"id":"PR-162","date":"2020-02-05T15:46:19","ref":["EN-159"],"code":["Removal of supragingival plaque and calculus from all teeth using dental instrument"],"stat":"completed","reasonCode":["Patient referral for dental care"],"endDate":"2020-02-05T16:19:14"},
{"id":"PR-163","date":"2020-02-05T16:19:14","ref":["EN-159"],"code":["Removal of subgingival plaque and calculus from all teeth using dental instrument"],"stat":"completed","reasonCode":["Patient referral for dental care"],"endDate":"2020-02-05T16:55:57"},
{"id":"PR-164","date":"2020-02-05T16:55:57","ref":["EN-159"],"code":["Dental plain X-ray bitewing"],"stat":"completed","endDate":"2020-02-05T17:25:57"},
{"id":"PR-165","date":"2020-02-05T16:55:57","ref":["EN-159"],"code":["Examination of gingivae"],"stat":"completed","reasonCode":["Patient referral for dental care"],"endDate":"2020-02-05T17:28:14"},
{"id":"PR-166","date":"2020-02-05T17:28:14","ref":["EN-159"],"code":["Oral health education"],"stat":"completed","reasonCode":["Patient referral for dental care"],"endDate":"2020-02-05T17:34:50"},
{"id":"PR-197","date":"2021-02-03T15:00:34","ref":["EN-176"],"code":["Medication reconciliation"],"stat":"completed","endDate":"2021-02-03T15:15:34"},
{"id":"PR-218","date":"2022-01-12T15:00:34","ref":["EN-207"],"code":["Patient referral for dental care"],"stat":"completed","endDate":"2022-01-12T15:14:08"},
{"id":"PR-238","date":"2022-01-19T15:00:34","ref":["EN-236"],"code":["Dental consultation and report"],"stat":"completed","reasonCode":["Patient referral for dental care"],"endDate":"2022-01-19T15:44:03"},
{"id":"PR-239","date":"2022-01-19T15:44:03","ref":["EN-236"],"code":["Dental care (regime/therapy)"],"stat":"completed","reasonCode":["Patient referral for dental care"],"endDate":"2022-01-19T16:36:49"},
{"id":"PR-240","date":"2022-01-19T16:36:49","ref":["EN-236"],"code":["Removal of supragingival plaque and calculus from all teeth using dental instrument"],"stat":"completed","reasonCode":["Patient referral for dental care"],"endDate":"2022-01-19T16:58:48"},
{"id":"PR-241","date":"2022-01-19T16:58:48","ref":["EN-236"],"code":["Removal of subgingival plaque and calculus from all teeth using dental instrument"],"stat":"completed","reasonCode":["Patient referral for dental care"],"endDate":"2022-01-19T17:30:34"},
{"id":"PR-242","date":"2022-01-19T17:30:34","ref":["EN-236"],"code":["Examination of gingivae"],"stat":"completed","reasonCode":["Patient referral for dental care"],"endDate":"2022-01-19T18:30:31"},
{"id":"PR-243","date":"2022-01-19T18:30:31","ref":["EN-236","CN-237"],"code":["Dental surgical procedure"],"stat":"completed","endDate":"2022-01-19T18:41:04"},
{"id":"PR-244","date":"2022-01-19T18:41:04","ref":["EN-236","CN-237"],"code":["Dental application of desensitizing medicament"],"stat":"completed","endDate":"2022-01-19T19:26:17"},
{"id":"PR-245","date":"2022-01-19T19:26:17","ref":["EN-236","CN-237"],"code":["Gingivectomy or gingivoplasty, per tooth"],"stat":"completed","endDate":"2022-01-19T20:08:19"},
{"id":"PR-246","date":"2022-01-19T20:08:19","ref":["EN-236"],"code":["Postoperative care for dental procedure (regime/therapy)"],"stat":"completed","endDate":"2022-01-19T20:49:55"},
{"id":"PR-247","date":"2022-01-19T20:49:55","ref":["EN-236"],"code":["Dental fluoride treatment"],"stat":"completed","reasonCode":["Patient referral for dental care"],"endDate":"2022-01-19T21:17:32"},
{"id":"PR-248","date":"2022-01-19T21:17:32","ref":["EN-236"],"code":["Oral health education"],"stat":"completed","reasonCode":["Patient referral for dental care"],"endDate":"2022-01-19T21:34:48"},
{"id":"PR-280","date":"2022-02-09T15:00:34","ref":["EN-268"],"code":["Depression screening"],"stat":"completed","endDate":"2022-02-09T15:15:22"},
{"id":"PR-281","date":"2022-02-09T15:15:22","ref":["EN-268"],"code":["Depression screening using Patient Health Questionnaire Nine Item score"],"stat":"completed","endDate":"2022-02-09T15:41:13"},
{"id":"PR-282","date":"2022-02-09T15:41:13","ref":["EN-268"],"code":["Assessment of substance use"],"stat":"completed","endDate":"2022-02-09T15:53:21"},
{"id":"PR-283","date":"2022-02-09T15:53:21","ref":["EN-268"],"code":["Assessment using Car, Relax, Alone, Forget, Friends, Trouble Screening Test"],"stat":"completed","endDate":"2022-02-09T16:12:15"},
{"id":"PR-284","date":"2022-02-09T16:12:15","ref":["EN-268","CN-269"],"code":["Health risks education"],"stat":"completed","endDate":"2022-02-09T16:27:05"},
{"id":"PR-309","date":"2023-02-15T15:00:34","ref":["EN-297"],"code":["Medication reconciliation"],"stat":"completed","endDate":"2023-02-15T15:15:34"},
{"id":"PR-310","date":"2023-02-15T15:00:34","ref":["EN-297"],"code":["Assessment of anxiety"],"stat":"completed","endDate":"2023-02-15T15:30:13"},
{"id":"PR-311","date":"2023-02-15T15:30:13","ref":["EN-297"],"code":["Depression screening"],"stat":"completed","endDate":"2023-02-15T15:45:03"},
{"id":"PR-312","date":"2023-02-15T15:45:03","ref":["EN-297"],"code":["Depression screening using Patient Health Questionnaire Nine Item score"],"stat":"completed","endDate":"2023-02-15T16:11:42"},
{"id":"PR-313","date":"2023-02-15T16:11:42","ref":["EN-297"],"code":["Assessment of substance use"],"stat":"completed","endDate":"2023-02-15T16:23:42"},
{"id":"PR-314","date":"2023-02-15T16:23:42","ref":["EN-297"],"code":["Assessment using Car, Relax, Alone, Forget, Friends, Trouble Screening Test"],"stat":"completed","endDate":"2023-02-15T16:45:57"},
{"id":"PR-315","date":"2023-02-15T16:45:57","ref":["EN-297"],"code":["Anticipatory guidance"],"stat":"completed","endDate":"2023-02-15T16:56:39"},
{"id":"PR-336","date":"2024-02-21T15:00:34","ref":["EN-323"],"code":["Medication reconciliation"],"stat":"completed","endDate":"2024-02-21T15:15:34"},
{"id":"PR-337","date":"2024-02-21T15:00:34","ref":["EN-323"],"code":["Assessment of anxiety"],"stat":"completed","endDate":"2024-02-21T15:21:55"},
{"id":"PR-338","date":"2024-02-21T15:21:55","ref":["EN-323"],"code":["Depression screening"],"stat":"completed","endDate":"2024-02-21T15:33:34"},
{"id":"PR-339","date":"2024-02-21T15:33:34","ref":["EN-323"],"code":["Depression screening using Patient Health Questionnaire Nine Item score"],"stat":"completed","endDate":"2024-02-21T15:57:02"}],

"Observation": [
{"id":"OB-9","date":"2014-12-31T15:00:34","ref":["EN-8"],"code":["Body Height is 102.9 cm"],"stat":"final","category":"Vital"},
{"id":"OB-10","date":"2014-12-31T15:00:34","ref":["EN-8"],"code":["Pain severity - 0-10 verbal numeric rating [Score] - Reported is 1 {score}"],"stat":"final","category":"Vital"},
{"id":"OB-11","date":"2014-12-31T15:00:34","ref":["EN-8"],"code":["Body Weight is 16.4 kg"],"stat":"final","category":"Vital"},
{"id":"OB-12","date":"2014-12-31T15:00:34","ref":["EN-8"],"code":["Body mass index (BMI) [Ratio] is 15.5 kg/m2"],"stat":"final","category":"Vital"},
{"id":"OB-13","date":"2014-12-31T15:00:34","ref":["EN-8"],"code":["Body mass index (BMI) [Percentile] Per age and sex is 60.211 %"],"stat":"final","category":"Vital"},
{"id":"OB-14","date":"2014-12-31T15:00:34","ref":["EN-8"],"code":["Blood pressure panel with all children optional","Diastolic Blood Pressure 70 mm[Hg]","Systolic Blood Pressure 105 mm[Hg]"],"stat":"final","category":"Vital"},
{"id":"OB-15","date":"2014-12-31T15:00:34","ref":["EN-8"],"code":["Heart rate is 73 /min"],"stat":"final","category":"Vital"},
{"id":"OB-16","date":"2014-12-31T15:00:34","ref":["EN-8"],"code":["Respiratory rate is 12 /min"],"stat":"final","category":"Vital"},
{"id":"OB-17","date":"2014-12-31T15:00:34","ref":["EN-8"],"code":["Tobacco smoking status is Never smoked tobacco (finding)"],"stat":"final","category":"Social"},
{"id":"OB-30","date":"2015-07-01T16:00:34","ref":["EN-28"],"code":["Body Height is 106.3 cm"],"stat":"final","category":"Vital"},
{"id":"OB-31","date":"2015-07-01T16:00:34","ref":["EN-28"],"code":["Pain severity - 0-10 verbal numeric rating [Score] - Reported is 2 {score}"],"stat":"final","category":"Vital"},
{"id":"OB-32","date":"2015-07-01T16:00:34","ref":["EN-28"],"code":["Body Weight is 17.8 kg"],"stat":"final","category":"Vital"},
{"id":"OB-33","date":"2015-07-01T16:00:34","ref":["EN-28"],"code":["Body mass index (BMI) [Ratio] is 15.76 kg/m2"],"stat":"final","category":"Vital"},
{"id":"OB-34","date":"2015-07-01T16:00:34","ref":["EN-28"],"code":["Body mass index (BMI) [Percentile] Per age and sex is 66.2 %"],"stat":"final","category":"Vital"},
{"id":"OB-35","date":"2015-07-01T16:00:34","ref":["EN-28"],"code":["Blood pressure panel with all children optional","Diastolic Blood Pressure 74 mm[Hg]","Systolic Blood Pressure 102 mm[Hg]"],"stat":"final","category":"Vital"},
{"id":"OB-36","date":"2015-07-01T16:00:34","ref":["EN-28"],"code":["Heart rate is 85 /min"],"stat":"final","category":"Vital"},
{"id":"OB-37","date":"2015-07-01T16:00:34","ref":["EN-28"],"code":["Respiratory rate is 14 /min"],"stat":"final","category":"Vital"},
{"id":"OB-38","date":"2015-07-01T16:00:34","ref":["EN-28"],"code":["Leukocytes [#/volume] in Blood by Automated count is 7.3257 10*3/uL"],"stat":"final","category":"Laboratory"},
{"id":"OB-39","date":"2015-07-01T16:00:34","ref":["EN-28"],"code":["Erythrocytes [#/volume] in Blood by Automated count is 4.9167 10*6/uL"],"stat":"final","category":"Laboratory"},
{"id":"OB-40","date":"2015-07-01T16:00:34","ref":["EN-28"],"code":["Hemoglobin [Mass/volume] in Blood is 16.046 g/dL"],"stat":"final","category":"Laboratory"},
{"id":"OB-41","date":"2015-07-01T16:00:34","ref":["EN-28"],"code":["Hematocrit [Volume Fraction] of Blood by Automated count is 40.04 %"],"stat":"final","category":"Laboratory"},
{"id":"OB-42","date":"2015-07-01T16:00:34","ref":["EN-28"],"code":["MCV [Entitic volume] by Automated count is 85.44 fL"],"stat":"final","category":"Laboratory"},
{"id":"OB-43","date":"2015-07-01T16:00:34","ref":["EN-28"],"code":["MCH [Entitic mass] by Automated count is 32.946 pg"],"stat":"final","category":"Laboratory"},
{"id":"OB-44","date":"2015-07-01T16:00:34","ref":["EN-28"],"code":["MCHC [Mass/volume] by Automated count is 33.455 g/dL"],"stat":"final","category":"Laboratory"},
{"id":"OB-45","date":"2015-07-01T16:00:34","ref":["EN-28"],"code":["Erythrocyte distribution width [Entitic volume] by Automated count is 45.167 fL"],"stat":"final","category":"Laboratory"},
{"id":"OB-46","date":"2015-07-01T16:00:34","ref":["EN-28"],"code":["Platelets [#/volume] in Blood by Automated count is 449.22 10*3/uL"],"stat":"final","category":"Laboratory"},
{"id":"OB-47","date":"2015-07-01T16:00:34","ref":["EN-28"],"code":["Platelet distribution width [Entitic volume] in Blood by Automated count is 278.26 fL"],"stat":"final","category":"Laboratory"},
{"id":"OB-48","date":"2015-07-01T16:00:34","ref":["EN-28"],"code":["Platelet mean volume [Entitic volume] in Blood by Automated count is 11.991 fL"],"stat":"final","category":"Laboratory"},
{"id":"OB-49","date":"2015-07-01T16:00:34","ref":["EN-28"],"code":["Tobacco smoking status is Never smoked tobacco (finding)"],"stat":"final","category":"Social"},
{"id":"OB-70","date":"2015-09-24T18:00:34","ref":["EN-68"],"code":["Body temperature","Oral temperature"],"stat":"final","category":"Vital","valueQuantity":"37.006 Cel"},
{"id":"OB-78","date":"2016-01-06T15:00:34","ref":["EN-76"],"code":["Body Height is 109.6 cm"],"stat":"final","category":"Vital"},
{"id":"OB-79","date":"2016-01-06T15:00:34","ref":["EN-76"],"code":["Pain severity - 0-10 verbal numeric rating [Score] - Reported is 3 {score}"],"stat":"final","category":"Vital"},
{"id":"OB-80","date":"2016-01-06T15:00:34","ref":["EN-76"],"code":["Body Weight is 19.3 kg"],"stat":"final","category":"Vital"},
{"id":"OB-81","date":"2016-01-06T15:00:34","ref":["EN-76"],"code":["Body mass index (BMI) [Ratio] is 16.02 kg/m2"],"stat":"final","category":"Vital"},
{"id":"OB-82","date":"2016-01-06T15:00:34","ref":["EN-76"],"code":["Body mass index (BMI) [Percentile] Per age and sex is 69.69 %"],"stat":"final","category":"Vital"},
{"id":"OB-83","date":"2016-01-06T15:00:34","ref":["EN-76"],"code":["Blood pressure panel with all children optional","Diastolic Blood Pressure 72 mm[Hg]","Systolic Blood Pressure 110 mm[Hg]"],"stat":"final","category":"Vital"},
{"id":"OB-84","date":"2016-01-06T15:00:34","ref":["EN-76"],"code":["Heart rate is 69 /min"],"stat":"final","category":"Vital"},
{"id":"OB-85","date":"2016-01-06T15:00:34","ref":["EN-76"],"code":["Respiratory rate is 15 /min"],"stat":"final","category":"Vital"},
{"id":"OB-86","date":"2016-01-06T15:00:34","ref":["EN-76"],"code":["Tobacco smoking status is Never smoked tobacco (finding)"],"stat":"final","category":"Social"},
{"id":"OB-95","date":"2017-01-11T15:00:34","ref":["EN-93"],"code":["Body Height is 116.1 cm"],"stat":"final","category":"Vital"},
{"id":"OB-96","date":"2017-01-11T15:00:34","ref":["EN-93"],"code":["Pain severity - 0-10 verbal numeric rating [Score] - Reported is 1 {score}"],"stat":"final","category":"Vital"},
{"id":"OB-97","date":"2017-01-11T15:00:34","ref":["EN-93"],"code":["Body Weight is 20.8 kg"],"stat":"final","category":"Vital"},
{"id":"OB-98","date":"2017-01-11T15:00:34","ref":["EN-93"],"code":["Body mass index (BMI) [Ratio] is 15.47 kg/m2"],"stat":"final","category":"Vital"},
{"id":"OB-99","date":"2017-01-11T15:00:34","ref":["EN-93"],"code":["Body mass index (BMI) [Percentile] Per age and sex is 50.965 %"],"stat":"final","category":"Vital"},
{"id":"OB-100","date":"2017-01-11T15:00:34","ref":["EN-93"],"code":["Blood pressure panel with all children optional","Diastolic Blood Pressure 72 mm[Hg]","Systolic Blood Pressure 99 mm[Hg]"],"stat":"final","category":"Vital"},
{"id":"OB-101","date":"2017-01-11T15:00:34","ref":["EN-93"],"code":["Heart rate is 98 /min"],"stat":"final","category":"Vital"},
{"id":"OB-102","date":"2017-01-11T15:00:34","ref":["EN-93"],"code":["Respiratory rate is 15 /min"],"stat":"final","category":"Vital"},
{"id":"OB-103","date":"2017-01-11T15:00:34","ref":["EN-93"],"code":["Tobacco smoking status is Never smoked tobacco (finding)"],"stat":"final","category":"Social"},
{"id":"OB-112","date":"2018-01-17T15:00:34","ref":["EN-110"],"code":["Body Height is 121.9 cm"],"stat":"final","category":"Vital"},
{"id":"OB-113","date":"2018-01-17T15:00:34","ref":["EN-110"],"code":["Pain severity - 0-10 verbal numeric rating [Score] - Reported is 3 {score}"],"stat":"final","category":"Vital"},
{"id":"OB-114","date":"2018-01-17T15:00:34","ref":["EN-110"],"code":["Body Weight is 24.1 kg"],"stat":"final","category":"Vital"},
{"id":"OB-115","date":"2018-01-17T15:00:34","ref":["EN-110"],"code":["Body mass index (BMI) [Ratio] is 16.24 kg/m2"],"stat":"final","category":"Vital"},
{"id":"OB-116","date":"2018-01-17T15:00:34","ref":["EN-110"],"code":["Body mass index (BMI) [Percentile] Per age and sex is 59.174 %"],"stat":"final","category":"Vital"},
{"id":"OB-117","date":"2018-01-17T15:00:34","ref":["EN-110"],"code":["Blood pressure panel with all children optional","Diastolic Blood Pressure 68 mm[Hg]","Systolic Blood Pressure 113 mm[Hg]"],"stat":"final","category":"Vital"},
{"id":"OB-118","date":"2018-01-17T15:00:34","ref":["EN-110"],"code":["Heart rate is 75 /min"],"stat":"final","category":"Vital"},
{"id":"OB-119","date":"2018-01-17T15:00:34","ref":["EN-110"],"code":["Respiratory rate is 15 /min"],"stat":"final","category":"Vital"},
{"id":"OB-120","date":"2018-01-17T15:00:34","ref":["EN-110"],"code":["Tobacco smoking status is Never smoked tobacco (finding)"],"stat":"final","category":"Social"},
{"id":"OB-127","date":"2019-01-23T15:00:34","ref":["EN-126"],"code":["Body Height is 127.3 cm"],"stat":"final","category":"Vital"},
{"id":"OB-128","date":"2019-01-23T15:00:34","ref":["EN-126"],"code":["Pain severity - 0-10 verbal numeric rating [Score] - Reported is 3 {score}"],"stat":"final","category":"Vital"},
{"id":"OB-129","date":"2019-01-23T15:00:34","ref":["EN-126"],"code":["Body Weight is 27.4 kg"],"stat":"final","category":"Vital"},
{"id":"OB-130","date":"2019-01-23T15:00:34","ref":["EN-126"],"code":["Body mass index (BMI) [Ratio] is 16.88 kg/m2"],"stat":"final","category":"Vital"},
{"id":"OB-131","date":"2019-01-23T15:00:34","ref":["EN-126"],"code":["Body mass index (BMI) [Percentile] Per age and sex is 60.27 %"],"stat":"final","category":"Vital"},
{"id":"OB-132","date":"2019-01-23T15:00:34","ref":["EN-126"],"code":["Blood pressure panel with all children optional","Diastolic Blood Pressure 73 mm[Hg]","Systolic Blood Pressure 110 mm[Hg]"],"stat":"final","category":"Vital"},
{"id":"OB-133","date":"2019-01-23T15:00:34","ref":["EN-126"],"code":["Heart rate is 86 /min"],"stat":"final","category":"Vital"},
{"id":"OB-134","date":"2019-01-23T15:00:34","ref":["EN-126"],"code":["Respiratory rate is 13 /min"],"stat":"final","category":"Vital"},
{"id":"OB-135","date":"2019-01-23T15:00:34","ref":["EN-126"],"code":["Tobacco smoking status is Never smoked tobacco (finding)"],"stat":"final","category":"Social"},
{"id":"OB-144","date":"2020-01-29T15:00:34","ref":["EN-142"],"code":["Body Height is 131.9 cm"],"stat":"final","category":"Vital"},
{"id":"OB-145","date":"2020-01-29T15:00:34","ref":["EN-142"],"code":["Pain severity - 0-10 verbal numeric rating [Score] - Reported is 2 {score}"],"stat":"final","category":"Vital"},
{"id":"OB-146","date":"2020-01-29T15:00:34","ref":["EN-142"],"code":["Body Weight is 28.3 kg"],"stat":"final","category":"Vital"},
{"id":"OB-147","date":"2020-01-29T15:00:34","ref":["EN-142"],"code":["Body mass index (BMI) [Ratio] is 16.27 kg/m2"],"stat":"final","category":"Vital"},
{"id":"OB-148","date":"2020-01-29T15:00:34","ref":["EN-142"],"code":["Body mass index (BMI) [Percentile] Per age and sex is 39.222 %"],"stat":"final","category":"Vital"},
{"id":"OB-149","date":"2020-01-29T15:00:34","ref":["EN-142"],"code":["Blood pressure panel with all children optional","Diastolic Blood Pressure 71 mm[Hg]","Systolic Blood Pressure 110 mm[Hg]"],"stat":"final","category":"Vital"},
{"id":"OB-150","date":"2020-01-29T15:00:34","ref":["EN-142"],"code":["Heart rate is 83 /min"],"stat":"final","category":"Vital"},
{"id":"OB-151","date":"2020-01-29T15:00:34","ref":["EN-142"],"code":["Respiratory rate is 13 /min"],"stat":"final","category":"Vital"},
{"id":"OB-152","date":"2020-01-29T15:00:34","ref":["EN-142"],"code":["Tobacco smoking status is Never smoked tobacco (finding)"],"stat":"final","category":"Social"},
{"id":"OB-177","date":"2021-02-03T15:00:34","ref":["EN-176"],"code":["Body Height is 137.3 cm"],"stat":"final","category":"Vital"},
{"id":"OB-178","date":"2021-02-03T15:00:34","ref":["EN-176"],"code":["Pain severity - 0-10 verbal numeric rating [Score] - Reported is 0 {score}"],"stat":"final","category":"Vital"},
{"id":"OB-179","date":"2021-02-03T15:00:34","ref":["EN-176"],"code":["Body Weight is 29.3 kg"],"stat":"final","category":"Vital"},
{"id":"OB-180","date":"2021-02-03T15:00:34","ref":["EN-176"],"code":["Body mass index (BMI) [Ratio] is 15.51 kg/m2"],"stat":"final","category":"Vital"},
{"id":"OB-181","date":"2021-02-03T15:00:34","ref":["EN-176"],"code":["Body mass index (BMI) [Percentile] Per age and sex is 17.537 %"],"stat":"final","category":"Vital"},
{"id":"OB-182","date":"2021-02-03T15:00:34","ref":["EN-176"],"code":["Blood pressure panel with all children optional","Diastolic Blood Pressure 69 mm[Hg]","Systolic Blood Pressure 112 mm[Hg]"],"stat":"final","category":"Vital"},
{"id":"OB-183","date":"2021-02-03T15:00:34","ref":["EN-176"],"code":["Heart rate is 83 /min"],"stat":"final","category":"Vital"},
{"id":"OB-184","date":"2021-02-03T15:00:34","ref":["EN-176"],"code":["Respiratory rate is 14 /min"],"stat":"final","category":"Vital"},
{"id":"OB-185","date":"2021-02-03T15:00:34","ref":["EN-176"],"code":["Leukocytes [#/volume] in Blood by Automated count is 7.2318 10*3/uL"],"stat":"final","category":"Laboratory"},
{"id":"OB-186","date":"2021-02-03T15:00:34","ref":["EN-176"],"code":["Erythrocytes [#/volume] in Blood by Automated count is 5.205 10*6/uL"],"stat":"final","category":"Laboratory"},
{"id":"OB-187","date":"2021-02-03T15:00:34","ref":["EN-176"],"code":["Hemoglobin [Mass/volume] in Blood is 17.427 g/dL"],"stat":"final","category":"Laboratory"},
{"id":"OB-188","date":"2021-02-03T15:00:34","ref":["EN-176"],"code":["Hematocrit [Volume Fraction] of Blood by Automated count is 40.369 %"],"stat":"final","category":"Laboratory"},
{"id":"OB-189","date":"2021-02-03T15:00:34","ref":["EN-176"],"code":["MCV [Entitic volume] by Automated count is 82.954 fL"],"stat":"final","category":"Laboratory"},
{"id":"OB-190","date":"2021-02-03T15:00:34","ref":["EN-176"],"code":["MCH [Entitic mass] by Automated count is 29.224 pg"],"stat":"final","category":"Laboratory"},
{"id":"OB-191","date":"2021-02-03T15:00:34","ref":["EN-176"],"code":["MCHC [Mass/volume] by Automated count is 34.775 g/dL"],"stat":"final","category":"Laboratory"},
{"id":"OB-192","date":"2021-02-03T15:00:34","ref":["EN-176"],"code":["Erythrocyte distribution width [Entitic volume] by Automated count is 45.284 fL"],"stat":"final","category":"Laboratory"},
{"id":"OB-193","date":"2021-02-03T15:00:34","ref":["EN-176"],"code":["Platelets [#/volume] in Blood by Automated count is 314.53 10*3/uL"],"stat":"final","category":"Laboratory"},
{"id":"OB-194","date":"2021-02-03T15:00:34","ref":["EN-176"],"code":["Platelet distribution width [Entitic volume] in Blood by Automated count is 510.49 fL"],"stat":"final","category":"Laboratory"},
{"id":"OB-195","date":"2021-02-03T15:00:34","ref":["EN-176"],"code":["Platelet mean volume [Entitic volume] in Blood by Automated count is 9.885 fL"],"stat":"final","category":"Laboratory"},
{"id":"OB-196","date":"2021-02-03T15:00:34","ref":["EN-176"],"code":["Tobacco smoking status is Never smoked tobacco (finding)"],"stat":"final","category":"Social"},
{"id":"OB-209","date":"2022-01-12T15:00:34","ref":["EN-207"],"code":["Body Height is 143.8 cm"],"stat":"final","category":"Vital"},
{"id":"OB-210","date":"2022-01-12T15:00:34","ref":["EN-207"],"code":["Pain severity - 0-10 verbal numeric rating [Score] - Reported is 3 {score}"],"stat":"final","category":"Vital"},
{"id":"OB-211","date":"2022-01-12T15:00:34","ref":["EN-207"],"code":["Body Weight is 32.6 kg"],"stat":"final","category":"Vital"},
{"id":"OB-212","date":"2022-01-12T15:00:34","ref":["EN-207"],"code":["Body mass index (BMI) [Ratio] is 15.79 kg/m2"],"stat":"final","category":"Vital"},
{"id":"OB-213","date":"2022-01-12T15:00:34","ref":["EN-207"],"code":["Body mass index (BMI) [Percentile] Per age and sex is 15.051 %"],"stat":"final","category":"Vital"},
{"id":"OB-214","date":"2022-01-12T15:00:34","ref":["EN-207"],"code":["Blood pressure panel with all children optional","Diastolic Blood Pressure 74 mm[Hg]","Systolic Blood Pressure 113 mm[Hg]"],"stat":"final","category":"Vital"},
{"id":"OB-215","date":"2022-01-12T15:00:34","ref":["EN-207"],"code":["Heart rate is 85 /min"],"stat":"final","category":"Vital"},
{"id":"OB-216","date":"2022-01-12T15:00:34","ref":["EN-207"],"code":["Respiratory rate is 14 /min"],"stat":"final","category":"Vital"},
{"id":"OB-217","date":"2022-01-12T15:00:34","ref":["EN-207"],"code":["Tobacco smoking status is Never smoked tobacco (finding)"],"stat":"final","category":"Social"},
{"id":"OB-270","date":"2022-02-09T15:00:34","ref":["EN-268"],"code":["Body Height is 144.4 cm"],"stat":"final","category":"Vital"},
{"id":"OB-271","date":"2022-02-09T15:00:34","ref":["EN-268"],"code":["Pain severity - 0-10 verbal numeric rating [Score] - Reported is 0 {score}"],"stat":"final","category":"Vital"},
{"id":"OB-272","date":"2022-02-09T15:00:34","ref":["EN-268"],"code":["Body Weight is 33 kg"],"stat":"final","category":"Vital"},
{"id":"OB-273","date":"2022-02-09T15:00:34","ref":["EN-268"],"code":["Body mass index (BMI) [Ratio] is 15.82 kg/m2"],"stat":"final","category":"Vital"},
{"id":"OB-274","date":"2022-02-09T15:00:34","ref":["EN-268"],"code":["Body mass index (BMI) [Percentile] Per age and sex is 14.942 %"],"stat":"final","category":"Vital"},
{"id":"OB-275","date":"2022-02-09T15:00:34","ref":["EN-268"],"code":["Blood pressure panel with all children optional","Diastolic Blood Pressure 71 mm[Hg]","Systolic Blood Pressure 109 mm[Hg]"],"stat":"final","category":"Vital"},
{"id":"OB-276","date":"2022-02-09T15:00:34","ref":["EN-268"],"code":["Heart rate is 64 /min"],"stat":"final","category":"Vital"},
{"id":"OB-277","date":"2022-02-09T15:00:34","ref":["EN-268"],"code":["Respiratory rate is 13 /min"],"stat":"final","category":"Vital"},
{"id":"OB-278","date":"2022-02-09T15:00:34","ref":["EN-268"],"code":["Tobacco smoking status is Never smoked tobacco (finding)"],"stat":"final","category":"Social"},
{"id":"OB-279","date":"2022-02-09T15:41:13","ref":["EN-268"],"code":["Patient Health Questionnaire-9: Modified for Teens total score [Reported.PHQ.Teen] is 0 {score}"],"stat":"final","category":"Survey"},
{"id":"OB-298","date":"2023-02-15T15:00:34","ref":["EN-297"],"code":["Body Height is 150.7 cm"],"stat":"final","category":"Vital"},
{"id":"OB-299","date":"2023-02-15T15:00:34","ref":["EN-297"],"code":["Pain severity - 0-10 verbal numeric rating [Score] - Reported is 3 {score}"],"stat":"final","category":"Vital"},
{"id":"OB-300","date":"2023-02-15T15:00:34","ref":["EN-297"],"code":["Body Weight is 38.6 kg"],"stat":"final","category":"Vital"},
{"id":"OB-301","date":"2023-02-15T15:00:34","ref":["EN-297"],"code":["Body mass index (BMI) [Ratio] is 16.99 kg/m2"],"stat":"final","category":"Vital"},
{"id":"OB-302","date":"2023-02-15T15:00:34","ref":["EN-297"],"code":["Body mass index (BMI) [Percentile] Per age and sex is 23.652 %"],"stat":"final","category":"Vital"},
{"id":"OB-303","date":"2023-02-15T15:00:34","ref":["EN-297"],"code":["Blood pressure panel with all children optional","Diastolic Blood Pressure 71 mm[Hg]","Systolic Blood Pressure 112 mm[Hg]"],"stat":"final","category":"Vital"},
{"id":"OB-304","date":"2023-02-15T15:00:34","ref":["EN-297"],"code":["Heart rate is 78 /min"],"stat":"final","category":"Vital"},
{"id":"OB-305","date":"2023-02-15T15:00:34","ref":["EN-297"],"code":["Respiratory rate is 13 /min"],"stat":"final","category":"Vital"},
{"id":"OB-306","date":"2023-02-15T15:00:34","ref":["EN-297"],"code":["Tobacco smoking status is Never smoked tobacco (finding)"],"stat":"final","category":"Social"},
{"id":"OB-307","date":"2023-02-15T15:30:13","ref":["EN-297"],"code":["Generalized anxiety disorder 7 item (GAD-7) total score [Reported.PHQ] is 9 {score}"],"stat":"final","category":"Survey"},
{"id":"OB-308","date":"2023-02-15T16:11:42","ref":["EN-297"],"code":["Patient Health Questionnaire-9: Modified for Teens total score [Reported.PHQ.Teen] is 2 {score}"],"stat":"final","category":"Survey"},
{"id":"OB-325","date":"2024-02-21T15:00:34","ref":["EN-323"],"code":["Body Height is 154.4 cm"],"stat":"final","category":"Vital"},
{"id":"OB-326","date":"2024-02-21T15:00:34","ref":["EN-323"],"code":["Pain severity - 0-10 verbal numeric rating [Score] - Reported is 3 {score}"],"stat":"final","category":"Vital"},
{"id":"OB-327","date":"2024-02-21T15:00:34","ref":["EN-323"],"code":["Body Weight is 39 kg"],"stat":"final","category":"Vital"},
{"id":"OB-328","date":"2024-02-21T15:00:34","ref":["EN-323"],"code":["Body mass index (BMI) [Ratio] is 16.37 kg/m2"],"stat":"final","category":"Vital"},
{"id":"OB-329","date":"2024-02-21T15:00:34","ref":["EN-323"],"code":["Body mass index (BMI) [Percentile] Per age and sex is 9.1125 %"],"stat":"final","category":"Vital"},
{"id":"OB-330","date":"2024-02-21T15:00:34","ref":["EN-323"],"code":["Blood pressure panel with all children optional","Diastolic Blood Pressure 74 mm[Hg]","Systolic Blood Pressure 110 mm[Hg]"],"stat":"final","category":"Vital"},
{"id":"OB-331","date":"2024-02-21T15:00:34","ref":["EN-323"],"code":["Heart rate is 94 /min"],"stat":"final","category":"Vital"},
{"id":"OB-332","date":"2024-02-21T15:00:34","ref":["EN-323"],"code":["Respiratory rate is 14 /min"],"stat":"final","category":"Vital"},
{"id":"OB-333","date":"2024-02-21T15:00:34","ref":["EN-323"],"code":["Tobacco smoking status is Never smoked tobacco (finding)"],"stat":"final","category":"Social"},
{"id":"OB-334","date":"2024-02-21T15:21:55","ref":["EN-323"],"code":["Generalized anxiety disorder 7 item (GAD-7) total score [Reported.PHQ] is 2 {score}"],"stat":"final","category":"Survey"},
{"id":"OB-335","date":"2024-02-21T15:57:02","ref":["EN-323"],"code":["Patient Health Questionnaire-9: Modified for Teens total score [Reported.PHQ.Teen] is 3 {score}"],"stat":"final","category":"Survey"
}],

"Immunization": [
{"id":"IM-19","date":"2014-12-31T15:00:34","ref":["EN-8"],"code":["varicella"],"stat":"completed","primarySource":true},
{"id":"IM-20","date":"2014-12-31T15:00:34","ref":["EN-8"],"code":["IPV"],"stat":"completed","primarySource":true},
{"id":"IM-21","date":"2014-12-31T15:00:34","ref":["EN-8"],"code":["Influenza, seasonal, injectable, preservative free"],"stat":"completed","primarySource":true},
{"id":"IM-22","date":"2014-12-31T15:00:34","ref":["EN-8"],"code":["DTaP"],"stat":"completed","primarySource":true},
{"id":"IM-23","date":"2014-12-31T15:00:34","ref":["EN-8"],"code":["MMR"],"stat":"completed","primarySource":true},
{"id":"IM-88","date":"2016-01-06T15:00:34","ref":["EN-76"],"code":["Influenza, seasonal, injectable, preservative free"],"stat":"completed","primarySource":true},
{"id":"IM-105","date":"2017-01-11T15:00:34","ref":["EN-93"],"code":["Influenza, seasonal, injectable, preservative free"],"stat":"completed","primarySource":true},
{"id":"IM-121","date":"2018-01-17T15:00:34","ref":["EN-110"],"code":["Influenza, seasonal, injectable, preservative free"],"stat":"completed","primarySource":true},
{"id":"IM-137","date":"2019-01-23T15:00:34","ref":["EN-126"],"code":["Influenza, seasonal, injectable, preservative free"],"stat":"completed","primarySource":true},
{"id":"IM-154","date":"2020-01-29T15:00:34","ref":["EN-142"],"code":["Influenza, seasonal, injectable, preservative free"],"stat":"completed","primarySource":true},
{"id":"IM-198","date":"2021-02-03T15:00:34","ref":["EN-176"],"code":["Tdap"],"stat":"completed","primarySource":true},
{"id":"IM-199","date":"2021-02-03T15:00:34","ref":["EN-176"],"code":["Influenza, seasonal, injectable, preservative free"],"stat":"completed","primarySource":true},
{"id":"IM-200","date":"2021-02-03T15:00:34","ref":["EN-176"],"code":["HPV, quadrivalent"],"stat":"completed","primarySource":true},
{"id":"IM-201","date":"2021-02-03T15:00:34","ref":["EN-176"],"code":["meningococcal MCV4P"],"stat":"completed","primarySource":true},
{"id":"IM-219","date":"2022-01-12T15:00:34","ref":["EN-207"],"code":["Influenza, seasonal, injectable, preservative free"],"stat":"completed","primarySource":true},
{"id":"IM-220","date":"2022-01-12T15:00:34","ref":["EN-207"],"code":["HPV, quadrivalent"],"stat":"completed","primarySource":true},
{"id":"IM-263","date":"2022-02-02T15:00:34","ref":["EN-262"],"code":["COVID-19, mRNA, LNP-S, PF, 30 mcg/0.3 mL dose"],"stat":"completed","primarySource":true},
{"id":"IM-285","date":"2022-02-09T15:00:34","ref":["EN-268"],"code":["HPV, quadrivalent"],"stat":"completed","primarySource":true},
{"id":"IM-292","date":"2022-02-23T15:00:34","ref":["EN-291"],"code":["COVID-19, mRNA, LNP-S, PF, 30 mcg/0.3 mL dose"],"stat":"completed","primarySource":true},
{"id":"IM-316","date":"2023-02-15T15:00:34","ref":["EN-297"],"code":["Influenza, seasonal, injectable, preservative free"],"stat":"completed","primarySource":true},
{"id":"IM-340","date":"2024-02-21T15:00:34","ref":["EN-323"],"code":["Influenza, seasonal, injectable, preservative free"],"stat":"completed","primarySource":true}],

"Medication": [
{"id":"MD-253","ref":[],"code":["sodium fluoride 0.0272 MG/MG Oral Gel"],"stat":"active"}],

"MedicationAdministration": [
{"id":"MA-257","date":"2022-01-19T20:49:55","ref":["EN-236"],"code":["sodium fluoride 0.0272 MG/MG Oral Gel","Patient referral for dental care"],"stat":"completed"}],

"AllergyIntolerance": []}